pymbse/optim/GeneticOptimization.py
pymbse/optim/__init__.py
pymbse/optim/cache_database_api.py
pymbse/optim/cockpit/OptimizationCockpit.py
pymbse/optim/cockpit/OptimizationCockpitWidget.py
pymbse/optim/cockpit/PeriodicTimer.py
pymbse/optim/cockpit/__init__.py
pymbse/optim/config/GeneticUpdateOperatorConfig.py
pymbse/optim/config/OptimizationConfig.py
pymbse/optim/config/__init__.py
pymbse/optim/constants.py
pymbse/optim/design_variable/DesignVariable.py
pymbse/optim/design_variable/DesignVariableBase.py
pymbse/optim/design_variable/DesignVariableFactory.py
pymbse/optim/design_variable/GeneticDesignVariable.py
pymbse/optim/design_variable/GeneticIndividual.py
pymbse/optim/design_variable/__init__.py
pymbse/optim/genetic/__init__.py
pymbse/optim/genetic/crossover_operators.py
pymbse/optim/genetic/mutation_operators.py
pymbse/optim/genetic/selection_operators.py
pymbse/optim/genetic/update_operators.py
pymbse/setup.py
pymbse_optim-0.0.11.dist-info/WHEEL
pymbse_optim-0.0.11.dist-info/METADATA
pymbse_optim-0.0.11.dist-info/RECORD
