Metadata-Version: 2.1
Name: pymbse-optim
Version: 0.0.11
Summary: 
Home-page: https://gitlab.cern.ch/chart-magnum/pymbse-commons
License: MIT
Author: mmaciejewski
Author-email: michal.maciejewski@ief.ee.ethz.ch
Requires-Python: >=3.9,<4.0
Classifier: Intended Audience :: Education
Classifier: License :: OSI Approved :: MIT License
Classifier: Operating System :: OS Independent
Classifier: Programming Language :: Python :: 3
Classifier: Programming Language :: Python :: 3.9
Classifier: Programming Language :: Python :: 3.10
Classifier: Programming Language :: Python :: 3
Requires-Dist: ipython (>=8.4.0,<9.0.0)
Requires-Dist: numpy (>=1.23.1,<2.0.0)
Requires-Dist: pandas (>=1.4.3,<2.0.0)
Requires-Dist: plotly (>=5.9.0,<6.0.0)
Requires-Dist: pydantic (>=1.9.1,<2.0.0)
Requires-Dist: pymbse-commons (>=0.0.6,<0.0.7)
Requires-Dist: requests (>=2.28.1,<3.0.0)
Project-URL: Repository, https://gitlab.cern.ch/chart-magnum/pymbse-commons
